huaweicloudsdkcae/__init__.py
huaweicloudsdkcae/v1/__init__.py
huaweicloudsdkcae/v1/cae_async_client.py
huaweicloudsdkcae/v1/cae_client.py
huaweicloudsdkcae/v1/model/__init__.py
huaweicloudsdkcae/v1/model/access.py
huaweicloudsdkcae/v1/model/access_configuration_data_items.py
huaweicloudsdkcae/v1/model/access_configuration_http_path.py
huaweicloudsdkcae/v1/model/access_configuration_metadata.py
huaweicloudsdkcae/v1/model/access_configuration_port.py
huaweicloudsdkcae/v1/model/access_control.py
huaweicloudsdkcae/v1/model/action_kind_obj.py
huaweicloudsdkcae/v1/model/action_on_component_build.py
huaweicloudsdkcae/v1/model/action_on_component_source.py
huaweicloudsdkcae/v1/model/action_on_component_spec.py
huaweicloudsdkcae/v1/model/agency.py
huaweicloudsdkcae/v1/model/agency_item.py
huaweicloudsdkcae/v1/model/agency_kind_obj.py
huaweicloudsdkcae/v1/model/agency_metadata.py
huaweicloudsdkcae/v1/model/api_version_obj.py
huaweicloudsdkcae/v1/model/app_info.py
huaweicloudsdkcae/v1/model/application_item.py
huaweicloudsdkcae/v1/model/application_kind_obj.py
huaweicloudsdkcae/v1/model/application_metadata.py
huaweicloudsdkcae/v1/model/archive.py
huaweicloudsdkcae/v1/model/build.py
huaweicloudsdkcae/v1/model/cert_item.py
huaweicloudsdkcae/v1/model/cert_req.py
huaweicloudsdkcae/v1/model/certificate_kind_obj.py
huaweicloudsdkcae/v1/model/cloud_storage_log_path_info.py
huaweicloudsdkcae/v1/model/component_configuration_kind_obj.py
huaweicloudsdkcae/v1/model/component_execution_result.py
huaweicloudsdkcae/v1/model/component_info.py
huaweicloudsdkcae/v1/model/component_item.py
huaweicloudsdkcae/v1/model/component_kind_obj.py
huaweicloudsdkcae/v1/model/component_snapshot_context.py
huaweicloudsdkcae/v1/model/component_snapshot_item.py
huaweicloudsdkcae/v1/model/component_snapshot_kind_obj.py
huaweicloudsdkcae/v1/model/component_spec.py
huaweicloudsdkcae/v1/model/configuration.py
huaweicloudsdkcae/v1/model/configuration_data.py
huaweicloudsdkcae-3.1.184.dist-info/METADATA
huaweicloudsdkcae-3.1.184.dist-info/WHEEL
huaweicloudsdkcae-3.1.184.dist-info/licenses/LICENSE
huaweicloudsdkcae-3.1.184.dist-info/RECORD
